trismid/__init__.py
trismid/trismid.py
trismid-0.0.0.dist-info/LICENSE
trismid-0.0.0.dist-info/METADATA
trismid-0.0.0.dist-info/WHEEL
trismid-0.0.0.dist-info/top_level.txt
trismid-0.0.0.dist-info/zip-safe
trismid-0.0.0.dist-info/RECORD
